features/__init__.py
features/date.py
prep/__init__.py
prep/encoding.py
prep/outliers.py
prep/pipeline.py
prep/scaling.py
prep/smote.py
split/__init__.py
split/sets.py
kellyml-0.1.5.dist-info/METADATA
kellyml-0.1.5.dist-info/WHEEL
kellyml-0.1.5.dist-info/top_level.txt
kellyml-0.1.5.dist-info/RECORD
